rtl/AxisTrans.v
module AxisTrans #(//include the adder
    parameter M = 4,                     // 输入整数位，最高位为符号位
    parameter N = 8,                      // 输入小数位
    parameter FUNC_TYPE = 0             // 0/1，选择功能类型(+,-)
)(
    input wire clk,
    input wire signed [M+N-1:0] f_in,    // 输入定点数（signed）
    input wire signed [M+N-1:0] s_in,
    output reg sign,                     // 输出符号位
    output reg signed [M+N-1:0] f_out    // 输出定点数的绝对值
);

always @(posedge clk) begin
    case (FUNC_TYPE)
        0: f_out <= s_in+f_in;
        1: f_out <= s_in-f_in;
    endcase
end

endmodule

rtl/PWL.v
module PWL #(
    parameter M = 2,                     // 输入整数位
    parameter N = 10,                     // 输入小数位
    parameter U = 8,                     // 查表索引位宽（使用输入高 U 位）
    parameter V = 4,                     // 分段内小数参与位宽（使用输入低 V 位）
    parameter K_WIDTH_I = 4,             // k 整数位宽
    parameter K_WIDTH_F = 12,            // k 小数位宽
    parameter B_WIDTH_I = 4,             // b 整数位宽
    parameter B_WIDTH_F = 12             // b 小数位宽
)(
    input wire clk,
    input wire signed [M+N-1:0] x_in,   // 输入定点数（signed）
    output reg signed [M+N-1:0] y_out   // 输出定点数（裁剪）
);

    localparam K_WIDTH = K_WIDTH_I + K_WIDTH_F;
    localparam B_WIDTH = B_WIDTH_I + B_WIDTH_F;
    localparam Y_FULL_WIDTH = K_WIDTH + V + 1; // k_frac 临时结果位宽，+1 防溢出
    localparam Y_TOTAL_WIDTH = (Y_FULL_WIDTH > B_WIDTH ? Y_FULL_WIDTH : B_WIDTH) + 1;

    // ROM 存储结构：k前b后
    reg [K_WIDTH + B_WIDTH - 1:0] rom [0:(1<<U)-1];

    initial begin
        $readmemh("D:\\Desktop\\Vivado\\work\\Flexible-Symmetry-Aware-Architecture\\parameter\\pwl_gelu_inputi0_inputf12_findLUT8_LinearCalc4_ki4kf12bi4bf12.mem", rom);  // 与 Python 输出的 .mem 对应
    end

    // 拆分输入：前 U 位用于查表，后 V 位用于乘法
    wire [U-1:0] idx  = x_in[M+N-1:M+N-U]; // 高 U 位
    wire signed [V:0] frac = {1'b0,x_in[V-1:0]};       // 低 V 位

    // 寄存器中间值
    reg signed [K_WIDTH-1:0] k;
    reg signed [B_WIDTH-1:0] b;
    reg signed [K_WIDTH+V-1:0] k_frac;
    reg signed [Y_TOTAL_WIDTH-1:0] y_full;
    reg signed [M+N-1:0] y_temp;

    always @(posedge clk) begin
        {k, b} <= rom[idx];
        k_frac <= k * frac;                        // k * frac (Qk * Qv)
        y_full <= (k_frac >>> V) + b;              // (k * frac) >> V + b

        // y_full 的小数位是 B_WIDTH_F，与目标 N 位对齐
        // 若 B_WIDTH_F > N，右移截取；若 B_WIDTH_F < N，左移补零
        if (B_WIDTH_F > N)
            y_temp <= y_full >>> (B_WIDTH_F - N);
        else
            y_temp <= y_full <<< (N - B_WIDTH_F);

        y_out <= y_temp;

    end

endmodule

rtl/Sym.v
module Sym #(
    parameter M = 4,                     // 输入整数位，最高位为符号位
    parameter N = 8,                     // 输入小数位
    parameter FUNC_TYPE = 0             // 0/1/2，选择功能类型(0,1,x)
)(
    input wire clk,
    input wire signed [M+N-1:0] x_in,    // 输入定点数（signed）
    input wire sign,                     // 输入符号位
    output reg signed [M+N-1:0] s_out    // 输出定点数（绝对值或其他）
);

always @(posedge clk) begin
    case (FUNC_TYPE)
        0: s_out <= 0;
        1: s_out <= (sign == 0) ? 0 : (1 << N);
        2: s_out <= (sign == 0) ? 0 : x_in;
        default: s_out <= 0;
    endcase
end

endmodule

rtl/Pre.v
module Pre #(
    parameter M = 4,                     // 输入整数位，最高位为符号位
    parameter N = 8                      // 输入小数位
)(
    input wire clk,
    input wire signed [M+N-1:0] x_in,    // 输入定点数（signed）
    output reg sign,                     // 输出符号位
    output reg signed [M+N-1:0] x_abs    // 输出定点数的绝对值
);

always @(posedge clk) begin
    sign <= x_in[M+N-1];                 // 记录符号位
    x_abs <= (x_in < 0) ? -x_in : x_in;  // 计算绝对值
end

endmodule

rtl/top.v
module top #(//include the adder
    parameter M = 2,                     // 输入整数位，最高位为符号位
    parameter N = 10,                      // 输入小数
    parameter FUNC_TYPE = 4             // 选择函数类型(Sigmoid,Tanh,Swish,GELU,Softplos)
)(
    input wire clk,
    input wire signed [M+N-1:0] x_in,    // 输入定点数（signed）
    output wire signed [M+N-1:0] f_out    // 输出定点数
);


wire sign;
wire [M+N-1:0] x_abs;

Pre #(
    .M(M),
    .N(N)
)pre_inst(
    .clk(clk),
    .x_in(x_in),
    .sign(sign),                     // 输出符号
    .x_abs(x_abs)    // 输出定点数的绝对值
);

wire [M+N-1:0] s_out;
Sym #(
    .M(M),
    .N(N),
    .FUNC_TYPE(FUNC_TYPE)             // 0/1/2，选择功能类型(0,1,x)
)sym_inst(
    .clk(clk),
    .x_in(x_in),
    .sign(sign),                     // 输入符号
    .s_out(s_out)    // 输出定点数（绝对值或其他）
);

wire [M+N-1:0] y_out;
PWL #(
    .M(M),
    .N(N),
    .U(8),
    .V(4),
    .K_WIDTH_I(4),
    .K_WIDTH_F(12),
    .B_WIDTH_I(4),
    .B_WIDTH_F(12)
) pwl_inst (
    .clk(clk),
    .x_in(x_abs),
    .y_out(y_out)
);

AxisTrans #(
    .M(M),
    .N(N),
    .FUNC_TYPE(FUNC_TYPE)             //选择功能类型(-,+)
)at_inst(
    .clk(clk),
    .f_in(y_out),
    .s_in(s_out),
    .f_out(f_out)    // 输出定点数
);

endmodule

tb/tb_top.v
`timescale 1ns / 1ps

module top_tb;

    // 参数定义（与 top 保持一致）
    parameter M = 2;
    parameter N = 10;
    parameter WIDTH = M + N;

    reg clk;
    reg signed [WIDTH-1:0] x_in;
    wire signed [WIDTH-1:0] f_out;

    // DUT 实例化
    top #(
        .M(M),
        .N(N),
        .FUNC_TYPE(4)  // 可切换测试 Swish, GELU, Softplus 等
    ) dut (
        .clk(clk),
        .x_in(x_in),
        .f_out(f_out)
    );

    // 时钟生成
    initial clk = 0;
    always #5 clk = ~clk;  // 10ns 周期

    // 仿真主流程
    initial begin
        // 初始化波形文件（可选）
        $dumpfile("top.vcd");
        $dumpvars(0, top_tb);

        $display("Time\tclk\tx_in\t\tf_out");

        $monitor("%0t\t%b\t%0d\t%0d", $time, clk, x_in, f_out);

        // 初始值
        x_in = 0;
        #100;

        // 测试用例 1：最大正值
        x_in = 12'sd2047;  // 1.999... (Q1.10)
        #10;

        // 测试用例 2：最大负值
        x_in = -12'sd2047; // -2.000
        #10;

        // 测试用例 3：中等正数
        x_in = 12'sd1024;  // 1.0
        #10;

        // 测试用例 4：中等负数
        x_in = -12'sd1024; // -1.0
        #10;

        // 测试用例 5：非常小数值（近零）
        x_in = 12'sd16;    // ~0.0156
        #10;

        // 测试用例 6：负小数值
        x_in = -12'sd16;
        #100;

        // 测试结束
        $display("Simulation complete.");
        $finish;
    end

endmodule

vivado/Flexible-Symmetry-Aware-Architecture.sim/sim_1/behav/xsim/top.vcd
$date
   Mon Jun  9 20:19:50 2025
$end

$version
  2023.2
  $dumpfile ("top.vcd") 
$end

$timescale
  1ps
$end

$scope module top_tb $end
$var reg 1 ! clk $end
$var reg 12 " x_in [11:0] $end
$var wire 12 # f_out [11:0] $end
$scope module dut $end
$var wire 1 $ clk $end
$var wire 12 % x_in [11:0] $end
$var wire 12 # f_out [11:0] $end
$var wire 1 & sign $end
$var wire 12 ' x_abs [11:0] $end
$var wire 12 ( s_out [11:0] $end
$var wire 12 ) y_out [11:0] $end
$scope module pre_inst $end
$var wire 1 $ clk $end
$var wire 12 % x_in [11:0] $end
$var reg 1 * sign $end
$var reg 12 + x_abs [11:0] $end
$upscope $end
$scope module sym_inst $end
$var wire 1 $ clk $end
$var wire 12 % x_in [11:0] $end
$var wire 1 & sign $end
$var reg 12 , s_out [11:0] $end
$upscope $end
$scope module pwl_inst $end
$var wire 1 $ clk $end
$var wire 12 ' x_in [11:0] $end
$var reg 12 - y_out [11:0] $end
$var wire 8 . idx [7:0] $end
$var wire 5 / frac [4:0] $end
$var reg 16 0 k [15:0] $end
$var reg 16 1 b [15:0] $end
$var reg 20 2 k_frac [19:0] $end
$var reg 22 3 y_full [21:0] $end
$var reg 12 4 y_temp [11:0] $end
$upscope $end
$scope module at_inst $end
$var wire 1 $ clk $end
$var wire 12 ) f_in [11:0] $end
$var wire 12 ( s_in [11:0] $end
$var reg 12 5 f_out [11:0] $end
$upscope $end
$upscope $end
$upscope $end
$enddefinitions $end

#0
$dumpvars
0!
b0 "
bx #
0$
b0 %
x&
bx '
bx (
bx )
x*
bx +
bx ,
bx -
bx .
b0xxxx /
bx 0
bx 1
bx 2
bx 3
bx 4
bx 5
$end

#5000
1!
1$
0&
b0 '
b0 (
0*
b0 +
b0 ,
b0 .
b0 /

#10000
0!
0$

#15000
1!
1$
b100000 0
b0 1

#20000
0!
0$

#25000
1!
1$
b0 2

#30000
0!
0$

#35000
1!
1$
b0 3

#40000
0!
0$

#45000
1!
1$
b0 4

#50000
0!
0$

#55000
1!
1$
b0 )
b0 -

#60000
0!
0$

#65000
1!
b0 #
1$
b0 5

#70000
0!
0$

#75000
1!
1$

#80000
0!
0$

#85000
1!
1$

#90000
0!
0$

#95000
1!
1$

#100000
0!
b11111111111 "
0$
b11111111111 %

#105000
1!
1$
b11111111111 '
b11111111111 +
b1111111 .
b1111 /

#110000
0!
b100000000001 "
0$
b100000000001 %

#115000
1!
1$
1&
1*
b1000110 0
b1111100000000 1
b111100000 2

#120000
0!
b10000000000 "
0$
b10000000000 %

#125000
1!
1$
0&
b10000000000 '
b10000000000 (
0*
b10000000000 +
b10000000000 ,
b1000000 .
b0 /
b10000011010 2
b1111100011110 3

#130000
0!
b110000000000 "
0$
b110000000000 %

#135000
1!
b10000000000 #
1$
1&
b0 (
1*
b0 ,
b1000101 0
b110101110110 1
b0 2
b1111101000001 3
b11111000111 4
b10000000000 5

#140000
0!
b10000 "
0$
b10000 %

#145000
1!
b0 #
1$
0&
b10000 '
b10000 (
b11111000111 )
0*
b10000 +
b10000 ,
b11111000111 -
b1 .
b110101110110 3
b11111010000 4
b0 5

#150000
0!
b111111110000 "
0$
b111111110000 %

#155000
1!
b11111010111 #
1$
1&
b0 (
b11111010000 )
1*
b0 ,
b11111010000 -
b100001 0
b100000 1
b1101011101 4
b11111010111 5

#160000
0!
0$

#165000
1!
b11111010000 #
1$
b111111110000 (
b1101011101 )
b111111110000 ,
b1101011101 -
b100000 3
b11111010000 5

#170000
0!
0$

#175000
1!
b1101001101 #
1$
b1000 4
b1101001101 5

#180000
0!
0$

#185000
1!
1$
b1000 )
b1000 -

#190000
0!
0$

#195000
1!
b111111111000 #
1$
b111111111000 5

